uart.v
module UART (
    input        reset,

    input        clock,
    input [15:0] clock_div,

    input [07:0] tx_data,
    input        tx_ready,
    output reg   tx,
    output reg   tx_done);

    reg        bit_clock;
    reg [15:0] clock_counter;

    reg [11:0] tx_state;
    reg [07:0] tx_buffer;
    reg        tx_loaded;
    reg        tx_ready_last;

    wire       tx_ready_edge;
    assign     tx_ready_edge = tx_ready && !tx_ready_last;

    parameter STATE_IDLE  = 11'b00000000001;
    parameter STATE_START = 11'b00000000010;
    parameter STATE_0     = 11'b00000000100;
    parameter STATE_1     = 11'b00000001000;
    parameter STATE_2     = 11'b00000010000;
    parameter STATE_3     = 11'b00000100000;
    parameter STATE_4     = 11'b00001000000;
    parameter STATE_5     = 11'b00010000000;
    parameter STATE_6     = 11'b00100000000;
    parameter STATE_7     = 11'b01000000000;
    parameter STATE_STOP  = 11'b10000000000;

    // Run the clock counter off the master clock
    always @(posedge clock or negedge reset)
    begin
        if (!reset)
            clock_counter <= 0;
        else if (clock_counter == clock_div)
            clock_counter <= 0;
        else
            clock_counter <= clock_counter + 1;
    end

    // Generate the bit clock from the clock counter
    always @(posedge clock or negedge reset)
    begin
        if (!reset)
            bit_clock <= 0;
        else if (clock_counter == clock_div)
            bit_clock <= ~bit_clock;
    end

    // Edge detect tx_ready
    always @(posedge clock or negedge reset)
    begin
        if (!reset)
            tx_ready_last <= 0;
        else
            tx_ready_last <= tx_ready;
    end

    // Load input data on rising edge of tx_ready
    always @(posedge clock or negedge reset)
    begin
        if (!reset)
        begin
            tx_loaded <= 0;
        end
        else
        begin
            if (tx_ready_edge)
            begin
                tx_buffer <= tx_data;
                tx_loaded <= 1;
            end
            else if (tx_state != STATE_IDLE)
            begin
                tx_loaded <= 0;
            end
        end
    end

    // UART TX state machine
    always @(posedge bit_clock or negedge reset)
    begin
        if (!reset)
        begin
            tx_state <= STATE_IDLE;
            tx_done  <= 1;
            tx       <= 1;
        end
        else
        begin
            case(tx_state)
                STATE_IDLE:
                begin
                    tx      <= 1;
                    if (tx_loaded)
                    begin
                        tx_state  <= STATE_START;
                        tx_done   <= 0;
                    end
                    else
                    begin
                        tx_done   <= 1;
                    end
                end

                STATE_START:
                begin
                    tx       <= 0;
                    tx_state <= STATE_0;
                end

                STATE_0:
                begin
                    tx       <= tx_buffer[0];
                    tx_state <= STATE_1;
                end

                STATE_1:
                begin
                    tx       <= tx_buffer[1];
                    tx_state <= STATE_2;
                end

                STATE_2:
                begin
                    tx       <= tx_buffer[2];
                    tx_state <= STATE_3;
                end

                STATE_3:
                begin
                    tx       <= tx_buffer[3];
                    tx_state <= STATE_4;
                end

                STATE_4:
                begin
                    tx       <= tx_buffer[4];
                    tx_state <= STATE_5;
                end

                STATE_5:
                begin
                    tx       <= tx_buffer[5];
                    tx_state <= STATE_6;
                end

                STATE_6:
                begin
                    tx       <= tx_buffer[6];
                    tx_state <= STATE_7;
                end

                STATE_7:
                begin
                    tx       <= tx_buffer[7];
                    tx_state <= STATE_STOP;
                end

                STATE_STOP:
                begin
                    tx       <= 1;
                    tx_done  <= 1;
                    tx_state <= STATE_IDLE;
                end

                default:
                begin
                    tx_state <= STATE_IDLE;
                end
            endcase
        end
    end
endmodule

uart_tb.v
`timescale 10ns / 1ns

module UART_TB();

    reg        clock;
    reg [15:0] clock_div = 15'd217;
    reg        reset;
    reg [07:0] tx_data;
    reg        tx_ready;

    wire tx;
    wire tx_done;

    initial begin
        clock = 0;
        reset = 1;
        tx_data = 8'd0;
        tx_ready = 0;
    end

    always
        #1 clock = ~clock;

    UART UART0 (
        .reset(reset),
        .clock(clock),
        .clock_div(clock_div),
        .tx_data(tx_data),
        .tx_ready(tx_ready),
        .tx(tx),
        .tx_done(tx_done)
    );

    initial begin
        $dumpfile("waveforms.vcd");
        $dumpvars();
        $display("Simulation starting...");

        #10

        $display("Resetting...");
        #10 reset = 0;
        #10 reset = 1;

        $display("Transmitting 8'b01000001...");
        #1 tx_ready = 0;
        #1 tx_data  = 8'b01000001;
        #1 tx_ready = 1;
        @(posedge tx_done);

        $display("Transmitting 8'b01000100...");
        #1 tx_ready = 0;
        #1 tx_data  = 8'b01000100;
        #1 tx_ready = 1;
        @(posedge tx_done);

        $display("Transmitting 8'b01000001...");
        #1 tx_ready = 0;
        #1 tx_data  = 8'b01000001;
        #1 tx_ready = 1;
        @(posedge tx_done);

        $display("Transmitting 8'b01001101...");
        #1 tx_ready = 0;
        #1 tx_data  = 8'b01001101;
        #1 tx_ready = 1;
        @(posedge tx_done);

        $display("Simulation complete.");
        $finish();
    end

    uart_decoder decoder(clock, tx);

endmodule

module uart_decoder(
    input clock,
    input tx);

    parameter uart_wait = 868;
    reg waiting_for_start = 0;
    reg [7:0] tx_byte;

    always @(posedge clock)
        uart_decoder;

    task uart_decoder;
    begin
        while (tx !== 1)
            @(tx);
        waiting_for_start = 1;
        while (tx !== 0)
            @(tx);
        waiting_for_start = 0;
        #(uart_wait/2)
        #uart_wait tx_byte[0] = tx;
        #uart_wait tx_byte[1] = tx;
        #uart_wait tx_byte[2] = tx;
        #uart_wait tx_byte[3] = tx;
        #uart_wait tx_byte[4] = tx;
        #uart_wait tx_byte[5] = tx;
        #uart_wait tx_byte[6] = tx;
        #uart_wait tx_byte[7] = tx;
        if (tx != 1)
        begin
            while (tx != 1)
                @(tx);
        end
        $display("%t %c (0x%h)", $time, tx_byte, tx_byte);
    end
    endtask
endmodule

waveforms.vcd
$date
	Sun May 25 21:42:00 2014
$end
$version
	Icarus Verilog
$end
$timescale
	1ns
$end
$scope module UART_TB $end
$var wire 1 ! tx $end
$var wire 1 " tx_done $end
$var reg 1 # clock $end
$var reg 16 $ clock_div [15:0] $end
$var reg 1 % reset $end
$var reg 8 & tx_data [7:0] $end
$var reg 1 ' tx_ready $end
$scope module UART0 $end
$var wire 1 ( clock $end
$var wire 16 ) clock_div [15:0] $end
$var wire 1 * reset $end
$var wire 8 + tx_data [7:0] $end
$var wire 1 , tx_ready $end
$var wire 1 - tx_ready_edge $end
$var reg 1 . bit_clock $end
$var reg 16 / clock_counter [15:0] $end
$var reg 1 0 tx $end
$var reg 8 1 tx_buffer [7:0] $end
$var reg 1 2 tx_done $end
$var reg 1 3 tx_loaded $end
$var reg 1 4 tx_ready_last $end
$var reg 12 5 tx_state [11:0] $end
$upscope $end
$scope module decoder $end
$var wire 1 ( clock $end
$var wire 1 ! tx $end
$var reg 8 6 tx_byte [7:0] $end
$var reg 1 7 waiting_for_start $end
$scope task uart_decoder $end
$upscope $end
$upscope $end
$upscope $end
$enddefinitions $end
#0
$dumpvars
07
bx 6
bx 5
x4
x3
x2
bx 1
x0
bx /
x.
0-
0,
b0 +
1*
b11011001 )
0(
0'
b0 &
1%
b11011001 $
0#
x"
x!
$end
#10
04
1#
1(
#20
0#
0(
#30
1#
1(
#40
0#
0(
#50
1#
1(
#60
0#
0(
#70
1#
1(
#80
0#
0(
#90
1#
1(
#100
0#
0(
#110
1#
1(
#120
0#
0(
#130
1#
1(
#140
0#
0(
#150
1#
1(
#160
0#
0(
#170
1#
1(
#180
0#
0(
#190
1#
1(
#200
17
10
1!
12
1"
b1 5
b0 /
0.
03
0#
0(
0%
0*
#210
1#
1(
#220
0#
0(
#230
1#
1(
#240
0#
0(
#250
1#
1(
#260
0#
0(
#270
1#
1(
#280
0#
0(
#290
1#
1(
#300
0#
0(
1%
1*
#310
b1 /
1#
1(
#320
0#
0(
b1000001 &
b1000001 +
#330
13
b1000001 1
14
b10 /
0-
1#
1(
1'
1,
#340
0#
0(
#350
b11 /
1#
1(
#360
0#
0(
#370
b100 /
1#
1(
#380
0#
0(
#390
b101 /
1#
1(
#400
0#
0(
#410
b110 /
1#
1(
#420
0#
0(
#430
b111 /
1#
1(
#440
0#
0(
#450
b1000 /
1#
1(
#460
0#
0(
#470
b1001 /
1#
1(
#480
0#
0(
#490
b1010 /
1#
1(
#500
0#
0(
#510
b1011 /
1#
1(
#520
0#
0(
#530
b1100 /
1#
1(
#540
0#
0(
#550
b1101 /
1#
1(
#560
0#
0(
#570
b1110 /
1#
1(
#580
0#
0(
#590
b1111 /
1#
1(
#600
0#
0(
#610
b10000 /
1#
1(
#620
0#
0(
#630
b10001 /
1#
1(
#640
0#
0(
#650
b10010 /
1#
1(
#660
0#
0(
#670
b10011 /
1#
1(
#680
0#
0(
#690
b10100 /
1#
1(
#700
0#
0(
#710
b10101 /
1#
1(
#720
0#
0(
#730
b10110 /
1#
1(
#740
0#
0(
#750
b10111 /
1#
1(
#760
0#
0(
#770
b11000 /
1#
1(
#780
0#
0(
#790
b11001 /
1#
1(
#800
0#
0(
#810
b11010 /
1#
1(
#820
0#
0(
#830
b11011 /
1#
1(
#840
0#
0(
#850
b11100 /
1#
1(
#860
0#
0(
#870
b11101 /
1#
1(
#880
0#
0(
#890
b11110 /
1#
1(
#900
0#
0(
#910
b11111 /
1#
1(
#920
0#
0(
#930
b100000 /
1#
1(
#940
0#
0(
#950
b100001 /
1#
1(
#960
0#
0(
#970
b100010 /
1#
1(
#980
0#
0(
#990
b100011 /
1#
1(
#1000
0#
0(
#1010
b100100 /
1#
1(
#1020
0#
0(
#1030
b100101 /
1#
1(
#1040
0#
0(
#1050
b100110 /
1#
1(
#1060
0#
0(
#1070
b100111 /
1#
1(
#1080
0#
0(
#1090
b101000 /
1#
1(
#1100
0#
0(
#1110
b101001 /
1#
1(
#1120
0#
0(
#1130
b101010 /
1#
1(
#1140
0#
0(
#1150
b101011 /
1#
1(
#1160
0#
0(
#1170
b101100 /
1#
1(
#1180
0#
0(
#1190
b101101 /
1#
1(
#1200
0#
0(
#1210
b101110 /
1#
1(
#1220
0#
0(
#1230
b101111 /
1#
1(
#1240
0#
0(
#1250
b110000 /
1#
1(
#1260
0#
0(
#1270
b110001 /
1#
1(
#1280
0#
0(
#1290
b110010 /
1#
1(
#1300
0#
0(
#1310
b110011 /
1#
1(
#1320
0#
0(
#1330
b110100 /
1#
1(
#1340
0#
0(
#1350
b110101 /
1#
1(
#1360
0#
0(
#1370
b110110 /
1#
1(
#1380
0#
0(
#1390
b110111 /
1#
1(
#1400
0#
0(
#1410
b111000 /
1#
1(
#1420
0#
0(
#1430
b111001 /
1#
1(
#1440
0#
0(
#1450
b111010 /
1#
1(
#1460
0#
0(
#1470
b111011 /
1#
1(
#1480
0#
0(
#1490
b111100 /
1#
1(
#1500
0#
0(
#1510
b111101 /
1#
1(
#1520
0#
0(
#1530
b111110 /
1#
1(
#1540
0#
0(
#1550
b111111 /
1#
1(
#1560
0#
0(
#1570
b1000000 /
1#
1(
#1580
0#
0(
#1590
b1000001 /
1#
1(
#1600
0#
0(
#1610
b1000010 /
1#
1(
#1620
0#
0(
#1630
b1000011 /
1#
1(
#1640
0#
0(
#1650
b1000100 /
1#
1(
#1660
0#
0(
#1670
b1000101 /
1#
1(
#1680
0#
0(
#1690
b1000110 /
1#
1(
#1700
0#
0(
#1710
b1000111 /
1#
1(
#1720
0#
0(
#1730
b1001000 /
1#
1(
#1740
0#
0(
#1750
b1001001 /
1#
1(
#1760
0#
0(
#1770
b1001010 /
1#
1(
#1780
0#
0(
#1790
b1001011 /
1#
1(
#1800
0#
0(
#1810
b1001100 /
1#
1(
#1820
0#
0(
#1830
b1001101 /
1#
1(
#1840
0#
0(
#1850
b1001110 /
1#
1(
#1860
0#
0(
#1870
b1001111 /
1#
1(
#1880
0#
0(
#1890
b1010000 /
1#
1(
#1900
0#
0(
#1910
b1010001 /
1#
1(
#1920
0#
0(
#1930
b1010010 /
1#
1(
#1940
0#
0(
#1950
b1010011 /
1#
1(
#1960
0#
0(
#1970
b1010100 /
1#
1(
#1980
0#
0(
#1990
b1010101 /
1#
1(
#2000
0#
0(
#2010
b1010110 /
1#
1(
#2020
0#
0(
#2030
b1010111 /
1#
1(
#2040
0#
0(
#2050
b1011000 /
1#
1(
#2060
0#
0(
#2070
b1011001 /
1#
1(
#2080
0#
0(
#2090
b1011010 /
1#
1(
#2100
0#
0(
#2110
b1011011 /
1#
1(
#2120
0#
0(
#2130
b1011100 /
1#
1(
#2140
0#
0(
#2150
b1011101 /
1#
1(
#2160
0#
0(
#2170
b1011110 /
1#
1(
#2180
0#
0(
#2190
b1011111 /
1#
1(
#2200
0#
0(
#2210
b1100000 /
1#
1(
#2220
0#
0(
#2230
b1100001 /
1#
1(
#2240
0#
0(
#2250
b1100010 /
1#
1(
#2260
0#
0(
#2270
b1100011 /
1#
1(
#2280
0#
0(
#2290
b1100100 /
1#
1(
#2300
0#
0(
#2310
b1100101 /
1#
1(
#2320
0#
0(
#2330
b1100110 /
1#
1(
#2340
0#
0(
#2350
b1100111 /
1#
1(
#2360
0#
0(
#2370
b1101000 /
1#
1(
#2380
0#
0(
#2390
b1101001 /
1#
1(
#2400
0#
0(
#2410
b1101010 /
1#
1(
#2420
0#
0(
#2430
b1101011 /
1#
1(
#2440
0#
0(
#2450
b1101100 /
1#
1(
#2460
0#
0(
#2470
b1101101 /
1#
1(
#2480
0#
0(
#2490
b1101110 /
1#
1(
#2500
0#
0(
#2510
b1101111 /
1#
1(
#2520
0#
0(
#2530
b1110000 /
1#
1(
#2540
0#
0(
#2550
b1110001 /
1#
1(
#2560
0#
0(
#2570
b1110010 /
1#
1(
#2580
0#
0(
#2590
b1110011 /
1#
1(
#2600
0#
0(
#2610
b1110100 /
1#
1(
#2620
0#
0(
#2630
b1110101 /
1#
1(
#2640
0#
0(
#2650
b1110110 /
1#
1(
#2660
0#
0(
#2670
b1110111 /
1#
1(
#2680
0#
0(
#2690
b1111000 /
1#
1(
#2700
0#
0(
#2710
b1111001 /
1#
1(
#2720
0#
0(
#2730
b1111010 /
1#
1(
#2740
0#
0(
#2750
b1111011 /
1#
1(
#2760
0#
0(
#2770
b1111100 /
1#
1(
#2780
0#
0(
#2790
b1111101 /
1#
1(
#2800
0#
0(
#2810
b1111110 /
1#
1(
#2820
0#
0(
#2830
b1111111 /
1#
1(
#2840
0#
0(
#2850
b10000000 /
1#
1(
#2860
0#
0(
#2870
b10000001 /
1#
1(
#2880
0#
0(
#2890
b10000010 /
1#
1(
#2900
0#
0(
#2910
b10000011 /
1#
1(
#2920
0#
0(
#2930
b10000100 /
1#
1(
#2940
0#
0(
#2950
b10000101 /
1#
1(
#2960
0#
0(
#2970
b10000110 /
1#
1(
#2980
0#
0(
#2990
b10000111 /
1#
1(
#3000
0#
0(
#3010
b10001000 /
1#
1(
#3020
0#
0(
#3030
b10001001 /
1#
1(
#3040
0#
0(
#3050
b10001010 /
1#
1(
#3060
0#
0(
#3070
b10001011 /
1#
1(
#3080
0#
0(
#3090
b10001100 /
1#
1(
#3100
0#
0(
#3110
b10001101 /
1#
1(
#3120
0#
0(
#3130
b10001110 /
1#
1(
#3140
0#
0(
#3150
b10001111 /
1#
1(
#3160
0#
0(
#3170
b10010000 /
1#
1(
#3180
0#
0(
#3190
b10010001 /
1#
1(
#3200
0#
0(
#3210
b10010010 /
1#
1(
#3220
0#
0(
#3230
b10010011 /
1#
1(
#3240
0#
0(
#3250
b10010100 /
1#
1(
#3260
0#
0(
#3270
b10010101 /
1#
1(
#3280
0#
0(
#3290
b10010110 /
1#
1(
#3300
0#
0(
#3310
b10010111 /
1#
1(
#3320
0#
0(
#3330
b10011000 /
1#
1(
#3340
0#
0(
#3350
b10011001 /
1#
1(
#3360
0#
0(
#3370
b10011010 /
1#
1(
#3380
0#
0(
#3390
b10011011 /
1#
1(
#3400
0#
0(
#3410
b10011100 /
1#
1(
#3420
0#
0(
#3430
b10011101 /
1#
1(
#3440
0#
0(
#3450
b10011110 /
1#
1(
#3460
0#
0(
#3470
b10011111 /
1#
1(
#3480
0#
0(
#3490
b10100000 /
1#
1(
#3500
0#
0(
#3510
b10100001 /
1#
1(
#3520
0#
0(
#3530
b10100010 /
1#
1(
#3540
0#
0(
#3550
b10100011 /
1#
1(
#3560
0#
0(
#3570
b10100100 /
1#
1(
#3580
0#
0(
#3590
b10100101 /
1#
1(
#3600
0#
0(
#3610
b10100110 /
1#
1(
#3620
0#
0(
#3630
b10100111 /
1#
1(
#3640
0#
0(
#3650
b10101000 /
1#
1(
#3660
0#
0(
#3670
b10101001 /
1#
1(
#3680
0#
0(
#3690
b10101010 /
1#
1(
#3700
0#
0(
#3710
b10101011 /
1#
1(
#3720
0#
0(
#3730
b10101100 /
1#
1(
#3740
0#
0(
#3750
b10101101 /
1#
1(
#3760
0#
0(
#3770
b10101110 /
1#
1(
#3780
0#
0(
#3790
b10101111 /
1#
1(
#3800
0#
0(
#3810
b10110000 /
1#
1(
#3820
0#
0(
#3830
b10110001 /
1#
1(
#3840
0#
0(
#3850
b10110010 /
1#
1(
#3860
0#
0(
#3870
b10110011 /
1#
1(
#3880
0#
0(
#3890
b10110100 /
1#
1(
#3900
0#
0(
#3910
b10110101 /
1#
1(
#3920
0#
0(
#3930
b10110110 /
1#
1(
#3940
0#
0(
#3950
b10110111 /
1#
1(
#3960
0#
0(
#3970
b10111000 /
1#
1(
#3980
0#
0(
#3990
b10111001 /
1#
1(
#4000
0#
0(
#4010
b10111010 /
1#
1(
#4020
0#
0(
#4030
b10111011 /
1#
1(
#4040
0#
0(
#4050
b10111100 /
1#
1(
#4060
0#
0(
#4070
b10111101 /
1#
1(
#4080
0#
0(
#4090
b10111110 /
1#
1(
#4100
0#
0(
#4110
b10111111 /
1#
1(
#4120
0#
0(
#4130
b11000000 /
1#
1(
#4140
0#
0(
#4150
b11000001 /
1#
1(
#4160
0#
0(
#4170
b11000010 /
1#
1(
#4180
0#
0(
#4190
b11000011 /
1#
1(
#4200
0#
0(
#4210
b11000100 /
1#
1(
#4220
0#
0(
#4230
b11000101 /
1#
1(
#4240
0#
0(
#4250
b11000110 /
1#
1(
#4260
0#
0(
#4270
b11000111 /
1#
1(
#4280
0#
0(
#4290
b11001000 /
1#
1(
#4300
0#
0(
#4310
b11001001 /
1#
1(
#4320
0#
0(
#4330
b11001010 /
1#
1(
#4340
0#
0(
#4350
b11001011 /
1#
1(
#4360
0#
0(
#4370
b11001100 /
1#
1(
#4380
0#
0(
#4390
b11001101 /
1#
1(
#4400
0#
0(
#4410
b11001110 /
1#
1(
#4420
0#
0(
#4430
b11001111 /
1#
1(
#4440
0#
0(
#4450
b11010000 /
1#
1(
#4460
0#
0(
#4470
b11010001 /
1#
1(
#4480
0#
0(
#4490
b11010010 /
1#
1(
#4500
0#
0(
#4510
b11010011 /
1#
1(
#4520
0#
0(
#4530
b11010100 /
1#
1(
#4540
0#
0(
#4550
b11010101 /
1#
1(
#4560
0#
0(
#4570
b11010110 /
1#
1(
#4580
0#
0(
#4590
b11010111 /
1#
1(
#4600
0#
0(
#4610
b11011000 /
1#
1(
#4620
0#
0(
#4630
b11011001 /
1#
1(
#4640
0#
0(
#4650
02
0"
b10 5
1.
b0 /
1#
1(
#4660
0#
0(
#4670
b1 /
03
1#
1(
#4680
0#
0(
#4690
b10 /
1#
1(
#4700
0#
0(
#4710
b11 /
1#
1(
#4720
0#
0(
#4730
b100 /
1#
1(
#4740
0#
0(
#4750
b101 /
1#
1(
#4760
0#
0(
#4770
b110 /
1#
1(
#4780
0#
0(
#4790
b111 /
1#
1(
#4800
0#
0(
#4810
b1000 /
1#
1(
#4820
0#
0(
#4830
b1001 /
1#
1(
#4840
0#
0(
#4850
b1010 /
1#
1(
#4860
0#
0(
#4870
b1011 /
1#
1(
#4880
0#
0(
#4890
b1100 /
1#
1(
#4900
0#
0(
#4910
b1101 /
1#
1(
#4920
0#
0(
#4930
b1110 /
1#
1(
#4940
0#
0(
#4950
b1111 /
1#
1(
#4960
0#
0(
#4970
b10000 /
1#
1(
#4980
0#
0(
#4990
b10001 /
1#
1(
#5000
0#
0(
#5010
b10010 /
1#
1(
#5020
0#
0(
#5030
b10011 /
1#
1(
#5040
0#
0(
#5050
b10100 /
1#
1(
#5060
0#
0(
#5070
b10101 /
1#
1(
#5080
0#
0(
#5090
b10110 /
1#
1(
#5100
0#
0(
#5110
b10111 /
1#
1(
#5120
0#
0(
#5130
b11000 /
1#
1(
#5140
0#
0(
#5150
b11001 /
1#
1(
#5160
0#
0(
#5170
b11010 /
1#
1(
#5180
0#
0(
#5190
b11011 /
1#
1(
#5200
0#
0(
#5210
b11100 /
1#
1(
#5220
0#
0(
#5230
b11101 /
1#
1(
#5240
0#
0(
#5250
b11110 /
1#
1(
#5260
0#
0(
#5270
b11111 /
1#
1(
#5280
0#
0(
#5290
b100000 /
1#
1(
#5300
0#
0(
#5310
b100001 /
1#
1(
#5320
0#
0(
#5330
b100010 /
1#
1(
#5340
0#
0(
#5350
b100011 /
1#
1(
#5360
0#
0(
#5370
b100100 /
1#
1(
#5380
0#
0(
#5390
b100101 /
1#
1(
#5400
0#
0(
#5410
b100110 /
1#
1(
#5420
0#
0(
#5430
b100111 /
1#
1(
#5440
0#
0(
#5450
b101000 /
1#
1(
#5460
0#
0(
#5470
b101001 /
1#
1(
#5480
0#
0(
#5490
b101010 /
1#
1(
#5500
0#
0(
#5510
b101011 /
1#
1(
#5520
0#
0(
#5530
b101100 /
1#
1(
#5540
0#
0(
#5550
b101101 /
1#
1(
#5560
0#
0(
#5570
b101110 /
1#
1(
#5580
0#
0(
#5590
b101111 /
1#
1(
#5600
0#
0(
#5610
b110000 /
1#
1(
#5620
0#
0(
#5630
b110001 /
1#
1(
#5640
0#
0(
#5650
b110010 /
1#
1(
#5660
0#
0(
#5670
b110011 /
1#
1(
#5680
0#
0(
#5690
b110100 /
1#
1(
#5700
0#
0(
#5710
b110101 /
1#
1(
#5720
0#
0(
#5730
b110110 /
1#
1(
#5740
0#
0(
#5750
b110111 /
1#
1(
#5760
0#
0(
#5770
b111000 /
1#
1(
#5780
0#
0(
#5790
b111001 /
1#
1(
#5800
0#
0(
#5810
b111010 /
1#
1(
#5820
0#
0(
#5830
b111011 /
1#
1(
#5840
0#
0(
#5850
b111100 /
1#
1(
#5860
0#
0(
#5870
b111101 /
1#
1(
#5880
0#
0(
#5890
b111110 /
1#
1(
#5900
0#
0(
#5910
b111111 /
1#
1(
#5920
0#
0(
#5930
b1000000 /
1#
1(
#5940
0#
0(
#5950
b1000001 /
1#
1(
#5960
0#
0(
#5970
b1000010 /
1#
1(
#5980
0#
0(
#5990
b1000011 /
1#
1(
#6000
0#
0(
#6010
b1000100 /
1#
1(
#6020
0#
0(
#6030
b1000101 /
1#
1(
#6040
0#
0(
#6050
b1000110 /
1#
1(
#6060
0#
0(
#6070
b1000111 /
1#
1(
#6080
0#
0(
#6090
b1001000 /
1#
1(
#6100
0#
0(
#6110
b1001001 /
1#
1(
#6120
0#
0(
#6130
b1001010 /
1#
1(
#6140
0#
0(
#6150
b1001011 /
1#
1(
#6160
0#
0(
#6170
b1001100 /
1#
1(
#6180
0#
0(
#6190
b1001101 /
1#
1(
#6200
0#
0(
#6210
b1001110 /
1#
1(
#6220
0#
0(
#6230
b1001111 /
1#
1(
#6240
0#
0(
#6250
b1010000 /
1#
1(
#6260
0#
0(
#6270
b1010001 /
1#
1(
#6280
0#
0(
#6290
b1010010 /
1#
1(
#6300
0#
0(
#6310
b1010011 /
1#
1(
#6320
0#
0(
#6330
b1010100 /
1#
1(
#6340
0#
0(
#6350
b1010101 /
1#
1(
#6360
0#
0(
#6370
b1010110 /
1#
1(
#6380
0#
0(
#6390
b1010111 /
1#
1(
#6400
0#
0(
#6410
b1011000 /
1#
1(
#6420
0#
0(
#6430
b1011001 /
1#
1(
#6440
0#
0(
#6450
b1011010 /
1#
1(
#6460
0#
0(
#6470
b1011011 /
1#
1(
#6480
0#
0(
#6490
b1011100 /
1#
1(
#6500
0#
0(
#6510
b1011101 /
1#
1(
#6520
0#
0(
#6530
b1011110 /
1#
1(
#6540
0#
0(
#6550
b1011111 /
1#
1(
#6560
0#
0(
#6570
b1100000 /
1#
1(
#6580
0#
0(
#6590
b1100001 /
1#
1(
#6600
0#
0(
#6610
b1100010 /
1#
1(
#6620
0#
0(
#6630
b1100011 /
1#
1(
#6640
0#
0(
#6650
b1100100 /
1#
1(
#6660
0#
0(
#6670
b1100101 /
1#
1(
#6680
0#
0(
#6690
b1100110 /
1#
1(
#6700
0#
0(
#6710
b1100111 /
1#
1(
#6720
0#
0(
#6730
b1101000 /
1#
1(
#6740
0#
0(
#6750
b1101001 /
1#
1(
#6760
0#
0(
#6770
b1101010 /
1#
1(
#6780
0#
0(
#6790
b1101011 /
1#
1(
#6800
0#
0(
#6810
b1101100 /
1#
1(
#6820
0#
0(
#6830
b1101101 /
1#
1(
#6840
0#
0(
#6850
b1101110 /
1#
1(
#6860
0#
0(
#6870
b1101111 /
1#
1(
#6880
0#
0(
#6890
b1110000 /
1#
1(
#6900
0#
0(
#6910
b1110001 /
1#
1(
#6920
0#
0(
#6930
b1110010 /
1#
1(
#6940
0#
0(
#6950
b1110011 /
1#
1(
#6960
0#
0(
#6970
b1110100 /
1#
1(
#6980
0#
0(
#6990
b1110101 /
1#
1(
#7000
0#
0(
#7010
b1110110 /
1#
1(
#7020
0#
0(
#7030
b1110111 /
1#
1(
#7040
0#
0(
#7050
b1111000 /
1#
1(
#7060
0#
0(
#7070
b1111001 /
1#
1(
#7080
0#
0(
#7090
b1111010 /
1#
1(
#7100
0#
0(
#7110
b1111011 /
1#
1(
#7120
0#
0(
#7130
b1111100 /
1#
1(
#7140
0#
0(
#7150
b1111101 /
1#
1(
#7160
0#
0(
#7170
b1111110 /
1#
1(
#7180
0#
0(
#7190
b1111111 /
1#
1(
#7200
0#
0(
#7210
b10000000 /
1#
1(
#7220
0#
0(
#7230
b10000001 /
1#
1(
#7240
0#
0(
#7250
b10000010 /
1#
1(
#7260
0#
0(
#7270
b10000011 /
1#
1(
#7280
0#
0(
#7290
b10000100 /
1#
1(
#7300
0#
0(
#7310
b10000101 /
1#
1(
#7320
0#
0(
#7330
b10000110 /
1#
1(
#7340
0#
0(
#7350
b10000111 /
1#
1(
#7360
0#
0(
#7370
b10001000 /
1#
1(
#7380
0#
0(
#7390
b10001001 /
1#
1(
#7400
0#
0(
#7410
b10001010 /
1#
1(
#7420
0#
0(
#7430
b10001011 /
1#
1(
#7440
0#
0(
#7450
b10001100 /
1#
1(
#7460
0#
0(
#7470
b10001101 /
1#
1(
#7480
0#
0(
#7490
b10001110 /
1#
1(
#7500
0#
0(
#7510
b10001111 /
1#
1(
#7520
0#
0(
#7530
b10010000 /
1#
1(
#7540
0#
0(
#7550
b10010001 /
1#
1(
#7560
0#
0(
#7570
b10010010 /
1#
1(
#7580
0#
0(
#7590
b10010011 /
1#
1(
#7600
0#
0(
#7610
b10010100 /
1#
1(
#7620
0#
0(
#7630
b10010101 /
1#
1(
#7640
0#
0(
#7650
b10010110 /
1#
1(
#7660
0#
0(
#7670
b10010111 /
1#
1(
#7680
0#
0(
#7690
b10011000 /
1#
1(
#7700
0#
0(
#7710
b10011001 /
1#
1(
#7720
0#
0(
#7730
b10011010 /
1#
1(
#7740
0#
0(
#7750
b10011011 /
1#
1(
#7760
0#
0(
#7770
b10011100 /
1#
1(
#7780
0#
0(
#7790
b10011101 /
1#
1(
#7800
0#
0(
#7810
b10011110 /
1#
1(
#7820
0#
0(
#7830
b10011111 /
1#
1(
#7840
0#
0(
#7850
b10100000 /
1#
1(
#7860
0#
0(
#7870
b10100001 /
1#
1(
#7880
0#
0(
#7890
b10100010 /
1#
1(
#7900
0#
0(
#7910
b10100011 /
1#
1(
#7920
0#
0(
#7930
b10100100 /
1#
1(
#7940
0#
0(
#7950
b10100101 /
1#
1(
#7960
0#
0(
#7970
b10100110 /
1#
1(
#7980
0#
0(
#7990
b10100111 /
1#
1(
#8000
0#
0(
#8010
b10101000 /
1#
1(
#8020
0#
0(
#8030
b10101001 /
1#
1(
#8040
0#
0(
#8050
b10101010 /
1#
1(
#8060
0#
0(
#8070
b10101011 /
1#
1(
#8080
0#
0(
#8090
b10101100 /
1#
1(
#8100
0#
0(
#8110
b10101101 /
1#
1(
#8120
0#
0(
#8130
b10101110 /
1#
1(
#8140
0#
0(
#8150
b10101111 /
1#
1(
#8160
0#
0(
#8170
b10110000 /
1#
1(
#8180
0#
0(
#8190
b10110001 /
1#
1(
#8200
0#
0(
#8210
b10110010 /
1#
1(
#8220
0#
0(
#8230
b10110011 /
1#
1(
#8240
0#
0(
#8250
b10110100 /
1#
1(
#8260
0#
0(
#8270
b10110101 /
1#
1(
#8280
0#
0(
#8290
b10110110 /
1#
1(
#8300
0#
0(
#8310
b10110111 /
1#
1(
#8320
0#
0(
#8330
b10111000 /
1#
1(
#8340
0#
0(
#8350
b10111001 /
1#
1(
#8360
0#
0(
#8370
b10111010 /
1#
1(
#8380
0#
0(
#8390
b10111011 /
1#
1(
#8400
0#
0(
#8410
b10111100 /
1#
1(
#8420
0#
0(
#8430
b10111101 /
1#
1(
#8440
0#
0(
#8450
b10111110 /
1#
1(
#8460
0#
0(
#8470
b10111111 /
1#
1(
#8480
0#
0(
#8490
b11000000 /
1#
1(
#8500
0#
0(
#8510
b11000001 /
1#
1(
#8520
0#
0(
#8530
b11000010 /
1#
1(
#8540
0#
0(
#8550
b11000011 /
1#
1(
#8560
0#
0(
#8570
b11000100 /
1#
1(
#8580
0#
0(
#8590
b11000101 /
1#
1(
#8600
0#
0(
#8610
b11000110 /
1#
1(
#8620
0#
0(
#8630
b11000111 /
1#
1(
#8640
0#
0(
#8650
b11001000 /
1#
1(
#8660
0#
0(
#8670
b11001001 /
1#
1(
#8680
0#
0(
#8690
b11001010 /
1#
1(
#8700
0#
0(
#8710
b11001011 /
1#
1(
#8720
0#
0(
#8730
b11001100 /
1#
1(
#8740
0#
0(
#8750
b11001101 /
1#
1(
#8760
0#
0(
#8770
b11001110 /
1#
1(
